setup.py
django_rest_utils.egg-info/PKG-INFO
django_rest_utils.egg-info/SOURCES.txt
django_rest_utils.egg-info/dependency_links.txt
django_rest_utils.egg-info/requires.txt
django_rest_utils.egg-info/top_level.txt
rest_utils/__init__.py
rest_utils/mixins.py
rest_utils/permissions.py
rest_utils/social_auth.py
rest_utils/tests.py
rest_utils/__pycache__/__init__.cpython-33.pyc
rest_utils/__pycache__/__init__.cpython-34.pyc
rest_utils/__pycache__/permissions.cpython-33.pyc
rest_utils/__pycache__/permissions.cpython-34.pyc
rest_utils/__pycache__/tests.cpython-33.pyc
rest_utils/__pycache__/tests.cpython-34.pyc
rest_utils/runtests/__init__.py
rest_utils/runtests/runtests.py
rest_utils/runtests/settings.py
rest_utils/runtests/__pycache__/__init__.cpython-33.pyc
rest_utils/runtests/__pycache__/__init__.cpython-34.pyc